hasp/__init__.py
hasp/_version.py
hasp/grating_priority.json
hasp/grating_priority.py
hasp/wrapper.py
hasp-1.2.5.dist-info/METADATA
hasp-1.2.5.dist-info/WHEEL
hasp-1.2.5.dist-info/entry_points.txt
hasp-1.2.5.dist-info/top_level.txt
hasp-1.2.5.dist-info/zip-safe
hasp-1.2.5.dist-info/RECORD
