Metadata-Version: 2.4
Name: hasp
Version: 1.2.5
Summary: Hubble Advanced Spectral Products creation code
Author-email: STScI <help@stsci.edu>
Project-URL: repository, https://github.com/spacetelescope/hasp
Project-URL: tracker, https://github.com/spacetelescope/hasp/issues
Classifier: Intended Audience :: Science/Research
Classifier: Topic :: Scientific/Engineering :: Astronomy
Classifier: License :: OSI Approved :: BSD License
Classifier: Programming Language :: Python :: 3
Requires-Python: >=3.8
Requires-Dist: astropy>=5.0.4
Requires-Dist: ullyses>=4.1.0
Provides-Extra: docs
Requires-Dist: numpydoc; extra == "docs"
Requires-Dist: packaging>=17; extra == "docs"
Requires-Dist: sphinx; extra == "docs"
Requires-Dist: sphinx-astropy; extra == "docs"
Requires-Dist: sphinx-rtd-theme; extra == "docs"
Requires-Dist: stsci-rtd-theme; extra == "docs"
Provides-Extra: test
Requires-Dist: psutil; extra == "test"
Requires-Dist: pytest>=4.6.0; extra == "test"
Requires-Dist: pytest-cov; extra == "test"
Provides-Extra: opencv
Requires-Dist: opencv-python>=4.6.0.66; extra == "opencv"
